ar6_utils/__init__.py
ar6_utils/constants.py
ar6_utils/data.py
ar6_utils/datavar.py
ar6_utils/generalutils.py
ar6_utils/importdata.py
ar6_utils/plot.py
ar6_utils/waterfall.py
ar6_utils/__pycache__/__init__.cpython-310.pyc
ar6_utils/__pycache__/__init__.cpython-311.pyc
ar6_utils/__pycache__/constants.cpython-310.pyc
ar6_utils/__pycache__/constants.cpython-311.pyc
ar6_utils/__pycache__/data.cpython-310.pyc
ar6_utils/__pycache__/data.cpython-311.pyc
ar6_utils/__pycache__/datavar.cpython-310.pyc
ar6_utils/__pycache__/datavar.cpython-311.pyc
ar6_utils/__pycache__/generalutils.cpython-310.pyc
ar6_utils/__pycache__/generalutils.cpython-311.pyc
ar6_utils/__pycache__/importdata.cpython-310.pyc
ar6_utils/__pycache__/importdata.cpython-311.pyc
ar6_utils/__pycache__/plot.cpython-310.pyc
ar6_utils/__pycache__/plot.cpython-311.pyc
ar6_utils/geodata/__init__.py
ar6_utils/geodata/macroregions.json
ar6_utils/geodata/__pycache__/__init__.cpython-310.pyc
ar6_utils/geodata/__pycache__/__init__.cpython-311.pyc
ar6_utils/geodata/__pycache__/__init__.cpython-37.pyc
ar6_utils/geodata/__pycache__/__init__.cpython-39.pyc
ar6_utils-0.1.1.dist-info/licenses/LICENSE
ar6_utils-0.1.1.dist-info/METADATA
ar6_utils-0.1.1.dist-info/WHEEL
ar6_utils-0.1.1.dist-info/top_level.txt
ar6_utils-0.1.1.dist-info/RECORD
