Metadata-Version: 2.4
Name: ar6_utils
Version: 0.1.1
Summary: Useful for handling AR6 database files in IAMC format, and provides AR6 plot style
Home-page: https://kvanderwijst.github.io/ar6_utils/
Author: Kaj-Ivar van der Wijst
Author-email: k.i.vanderwijst@gmail.com
License:                     GNU GENERAL PUBLIC LICENSE
License-File: LICENSE
Requires-Dist: numpy
Requires-Dist: pandas
Requires-Dist: plotly
Requires-Dist: openpyxl
Dynamic: author
Dynamic: author-email
Dynamic: description
Dynamic: home-page
Dynamic: license
Dynamic: license-file
Dynamic: requires-dist
Dynamic: summary
